README.md
setup.py
vk_advanced_api/API.py
vk_advanced_api/Auth.py
vk_advanced_api/Pool.py
vk_advanced_api/Request.py
vk_advanced_api/Response.py
vk_advanced_api/__init__.py
vk_advanced_api/version
vk_advanced_api/vkapi.py
vk_advanced_api.egg-info/PKG-INFO
vk_advanced_api.egg-info/SOURCES.txt
vk_advanced_api.egg-info/dependency_links.txt
vk_advanced_api.egg-info/requires.txt
vk_advanced_api.egg-info/top_level.txt