Metadata-Version: 1.0
Name: vk-advanced-api
Version: 1.3.1.2
Summary: Simple to use OpenSource Lib for API VK
Home-page: https://github.com/Ar4ikov/vk_advanced_api
Author: Nikita Archikov
Author-email: bizy18588@gmail.com
License: MIT License
Keywords: opensource vk api wrappper ar4ikov vkadvancedapi vk_advanced_api
Platform: UNKNOWN
